tufup/__init__.py
tufup/__main__.py
tufup/client.py
tufup/common.py
tufup/repo/__init__.py
tufup/repo/cli.py
tufup/utils/__init__.py
tufup/utils/platform_specific.py
tufup-0.9.0.dist-info/LICENSE
tufup-0.9.0.dist-info/METADATA
tufup-0.9.0.dist-info/WHEEL
tufup-0.9.0.dist-info/entry_points.txt
tufup-0.9.0.dist-info/top_level.txt
tufup-0.9.0.dist-info/RECORD
