Metadata-Version: 2.1
Name: tufup
Version: 0.9.0
Summary: Automated updates for stand-alone Python applications, built upon python-tuf.
Author-email: dennisvang <djvg@protonmail.com>
License: MIT License
Project-URL: source, https://github.com/dennisvang/tufup
Project-URL: documentation, https://tufup.readthedocs.io/en/latest/
Project-URL: issues, https://github.com/dennisvang/tufup/issues
Classifier: Programming Language :: Python :: 3
Classifier: License :: OSI Approved :: MIT License
Classifier: Operating System :: OS Independent
Requires-Python: >=3.8
License-File: LICENSE
Requires-Dist: bsdiff4 ==1.2.*
Requires-Dist: packaging >=21.3
Requires-Dist: securesystemslib[crypto,pynacl] >=0.26.0
Requires-Dist: setuptools >=65.5.1
Requires-Dist: tuf ==4.0.*
Requires-Dist: certifi >=2022.12.7
Requires-Dist: cryptography >=38.0.3
